MetaLogo/__init__.py
MetaLogo/character.py
MetaLogo/colors.py
MetaLogo/column.py
MetaLogo/connect.py
MetaLogo/entry.py
MetaLogo/item.py
MetaLogo/logo.py
MetaLogo/logobits.py
MetaLogo/pholy.py
MetaLogo/utils.py
MetaLogo/version.py
MetaLogo-1.1.1.dist-info/LICENSE
MetaLogo-1.1.1.dist-info/METADATA
MetaLogo-1.1.1.dist-info/WHEEL
MetaLogo-1.1.1.dist-info/entry_points.txt
MetaLogo-1.1.1.dist-info/top_level.txt
MetaLogo-1.1.1.dist-info/RECORD
