Metadata-Version: 2.1
Name: MetaLogo
Version: 1.1.1
Summary: MetaLogo is a heterogeneity-aware sequence logo generator and aligner
Home-page: https://github.com/labomics/MetaLogo
Author: Yaowen Chen
Author-email: achenge07@163.com
License: UNKNOWN
Platform: UNKNOWN
Requires-Python: >=3.6
License-File: LICENSE
Requires-Dist: biopython (>=1.77)
Requires-Dist: matplotlib (>=3.3.0)
Requires-Dist: numpy (>=1.19.1)
Requires-Dist: pandas (>=1.3.0)
Requires-Dist: scipy (>=1.5.2)
Requires-Dist: seaborn (>=0.11.1)
Requires-Dist: toml (>=0.10.2)
Requires-Dist: treecluster (>=1.0.3)
Requires-Dist: dendropy (>=4.5.2)
Requires-Dist: ete3 (>=3.1.1)
Provides-Extra: webserver
Requires-Dist: dash (==1.21.0) ; extra == 'webserver'
Requires-Dist: dash-bio (==0.8.0) ; extra == 'webserver'
Requires-Dist: dash-bootstrap-components (==0.12.2) ; extra == 'webserver'
Requires-Dist: Flask (==2.0.1) ; extra == 'webserver'
Requires-Dist: gunicorn (==20.1.0) ; extra == 'webserver'
Requires-Dist: plotly (==5.1.0) ; extra == 'webserver'
Requires-Dist: supervisor (==4.2.2) ; extra == 'webserver'
Requires-Dist: rq (==1.10.0) ; extra == 'webserver'
Requires-Dist: hiredis (==2.0.0) ; extra == 'webserver'
